{"case_case1.md":"c09e4b0c","case_case2.md":"abcb056d","case_case3.md":"eba6f44d","case_case4.md":"a6091cab","case_index.md":"b9a2f2a3","developer_index.md":"1075f4bf","developer_l10n.md":"80ff5d0f","developer_theme.md":"2f9a08a0","en_us_case_case1.md":"44f4d3f2","en_us_case_case2.md":"ecbe83e1","en_us_case_case3.md":"b63e1754","en_us_case_case4.md":"6b10d5c1","en_us_case_index.md":"1d6196a6","en_us_developer_index.md":"3680d623","en_us_developer_l10n.md":"c75d30ce","en_us_developer_theme.md":"72c8d925","en_us_guide_agent.md":"8a0d8548","en_us_guide_agentq.md":"0c0351af","en_us_guide_api.md":"79b6188a","en_us_guide_dashboard.md":"eb99ef39","en_us_guide_dashboardq.md":"cbd5cf4c","en_us_guide_loginq.md":"8e7c8a14","en_us_guide_notifications.md":"ead8f912","en_us_guide_q2.md":"8323ac4b","en_us_guide_q3.md":"ef24c58e","en_us_guide_q4.md":"414e3c69","en_us_guide_q5.md":"583fa2c8","en_us_guide_q6.md":"f61dac5f","en_us_guide_servers.md":"02a9e02b","en_us_guide_services.md":"772dbb29","en_us_guide_settings.md":"2d9dfb43","en_us_guide_tasks.md":"3eebcd2a","en_us_index.md":"d699e8ab","guide_agent.md":"f3f39baf","guide_agentq.md":"20d39a69","guide_api.md":"f50dd0eb","guide_dashboard.md":"c477b3f9","guide_dashboardq.md":"16db81d1","guide_loginq.md":"7a122b0a","guide_notifications.md":"825d41b0","guide_q1.md":"370cf8e8","guide_q2.md":"12b78101","guide_q3.md":"9ed43395","guide_q4.md":"f8391813","guide_q5.md":"4b2106e2","guide_q6.md":"df9c3083","guide_servers.md":"6fb16960","guide_services.md":"8d7a784d","guide_settings.md":"68b4c8b0","guide_tasks.md":"79fcc93d","index.md":"777deff1"}
