{"en_us_case_case1.md":"BraHvlgE","en_us_case_case3.md":"CXdArAfV","en_us_guide_dashboard.md":"IAKxUCxk","case_index.md":"CL56yXw-","developer_theme.md":"CfFaPJHY","en_us_guide_servers.md":"XQejGsSi","en_us_guide_tasks.md":"DU-6LtoC","en_us_index.md":"BFJMY7JM","guide_agentq.md":"_rmJhPsl","guide_dashboardq.md":"D32G9OEQ","guide_loginq.md":"CZ_8LbD6","guide_q2.md":"eGLvmANK","guide_api.md":"B6j89lxB","guide_q4.md":"DOJVnMdI","guide_q5.md":"B7LLFbiP","guide_q3.md":"CmXVQATa","guide_q7.md":"DsOlVXjH","guide_q6.md":"DJvdtQgS","guide_servers.md":"B4eeJ4Bm","guide_q8.md":"kKu1iLFh","guide_q9.md":"qE5MO02L","guide_services.md":"C3MLrZZR","guide_tasks.md":"PGFQInxq","en_us_guide_q6.md":"BuezOVXG","en_us_guide_q7.md":"-0Fp7z5x","en_us_guide_dashboardq.md":"BLzwbzCJ","en_us_guide_q5.md":"COGzAeKo","case_case3.md":"DEI3MTl0","en_us_guide_q8.md":"CvKuBi3w","en_us_guide_notifications.md":"CzLtgVKn","case_case4.md":"CXDl4wcm","developer_l10n.md":"iHv70E2_","en_us_guide_services.md":"MGhKMJ8G","guide_settings.md":"BYk6vGQ3","case_case1.md":"BGyfa1Bl","en_us_guide_q2.md":"Bp7X-6bb","en_us_developer_l10n.md":"BQjj7YDS","en_us_guide_q4.md":"Iv-W_P5U","en_us_guide_q3.md":"YormCwG5","en_us_case_index.md":"BCmCB96F","case_case5.md":"BcWkSPYi","en_us_developer_index.md":"vCv6fdms","developer_index.md":"Bk47pngF","en_us_case_case4.md":"pifNT2cZ","en_us_developer_theme.md":"DxRNO9UW","en_us_case_case2.md":"B3B7WMGF","en_us_guide_api.md":"Dni33a3H","en_us_case_case5.md":"DgPlQZV_","index.md":"CMjTAWgc","en_us_guide_q9.md":"D_PhynZb","en_us_guide_loginq.md":"D3Z56OkQ","case_case2.md":"CnuKxxiC","en_us_guide_agent.md":"DlLJ0Yp5","guide_q1.md":"By2wEVoV","en_us_guide_agentq.md":"pLT_iNiH","guide_agent.md":"BNdp2k15","en_us_guide_settings.md":"FZoi-siH","guide_dashboard.md":"Cf-R2oQB","guide_notifications.md":"DFWSZjrA"}
