{"case_index.md":"DkyNBWvq","case_case3.md":"pTnx8Jyl","en_us_case_case7.md":"DUz8eaJM","en_us_case_case6.md":"CD6eIXmm","case_case6.md":"B5v9MZ09","case_case2.md":"X3Wfp--4","guide_q10.md":"C-HelGXr","en_us_guide_services.md":"RLK1LLjh","guide_q1.md":"OItkeTKh","en_us_guide_servers.md":"pbLiiBsH","en_us_case_case2.md":"dTqGaOM0","case_case4.md":"HtGoy7Fw","en_us_case_case5.md":"BO2R-Yv-","guide_q6.md":"D_5rElWi","en_us_guide_tasks.md":"CM8MicrI","guide_ddns.md":"DW-GVviF","guide_group.md":"Bo18ZZl9","guide_q5.md":"BMFXlFom","en_us_guide_agentq.md":"CF3eaz3O","developer_index.md":"P4em_uIY","guide_settings.md":"D6E792yV","developer_l10n.md":"fzAlApOL","case_case1.md":"DkiqWDNM","guide_q4.md":"CwTotfm_","en_us_guide_q4.md":"DzeagG4V","en_us_guide_q7.md":"n-76n7hH","en_us_guide_q6.md":"CxuTRE9d","en_us_case_case4.md":"BpPLN_JY","guide_q11.md":"J75WNdm1","guide_q9.md":"B6KMov6L","guide_q3.md":"Best5-Xe","guide_agent.md":"B7oFOJko","developer_theme.md":"Cvm9EqXz","guide_services.md":"Bm8SLon6","guide_notifications.md":"DmeryfzH","en_us_developer_l10n.md":"B7cWIpsq","en_us_guide_q11.md":"3CkKxGC9","guide_loginq.md":"BEQX9uOq","guide_nat.md":"DmE31fSn","en_us_developer_index.md":"B-U83v0F","guide_tasks.md":"BAxvpasL","index.md":"D-ZY14gm","en_us_guide_api.md":"Boli9IdL","case_case7.md":"CITe8I5P","en_us_guide_ddns.md":"BeRO-jAU","en_us_case_case3.md":"Bx1fBF4Y","guide_agentq.md":"B3GgnTtG","en_us_index.md":"2_yE3kKo","guide_api.md":"DgD4KKdp","guide_dashboard.md":"B8ylBIvf","guide_dashboardq.md":"P7siN2ZF","en_us_case_case1.md":"BWCa6N1B","en_us_guide_agent.md":"B33kJkBF","en_us_guide_dashboard.md":"Crd9QzYY","en_us_guide_dashboardq.md":"uE8rNuOB","guide_servers.md":"Ctkf7HoS","en_us_developer_theme.md":"DlIVcgEX","en_us_case_index.md":"BgwhMhi4","case_case5.md":"_X15GFzP","en_us_guide_q5.md":"Bx8GBfZk","en_us_guide_settings.md":"C2Sc_LV6","en_us_guide_notifications.md":"BGRAuKt5","en_us_guide_q9.md":"D5cP-_Jq","guide_q2.md":"Dc0bIcPq","en_us_guide_q10.md":"qQHp4wYa","en_us_guide_q2.md":"zy5x5i8G","en_us_guide_q8.md":"B-GS5SN7","guide_q8.md":"kuYU6tEY","guide_q7.md":"1e3gz7UN","en_us_guide_q3.md":"gmmUbT0i","en_us_guide_nat.md":"BiONeeT5","en_us_guide_loginq.md":"EU4Jx7NG"}
