{"case_case1.md":"c57845bb","case_case2.md":"4e2f3d59","case_case3.md":"9ffcf258","case_case4.md":"5f197345","case_index.md":"25117d67","developer_index.md":"09847710","developer_l10n.md":"0fdea9dc","developer_theme.md":"3043d0d6","en_us_case_case1.md":"f6af273d","en_us_case_case2.md":"45d8419d","en_us_case_case3.md":"576acd4f","en_us_case_case4.md":"c13e3d57","en_us_case_index.md":"e85c2b5e","en_us_developer_index.md":"d73c8d72","en_us_developer_l10n.md":"16739d39","en_us_developer_theme.md":"b6e991af","en_us_guide_agent.md":"04858606","en_us_guide_agentq.md":"6f4fa583","en_us_guide_api.md":"afd899f0","en_us_guide_dashboard.md":"9baceaf6","en_us_guide_dashboardq.md":"09a5d0a0","en_us_guide_loginq.md":"1af6198f","en_us_guide_notifications.md":"b869c13b","en_us_guide_q2.md":"d84fe347","en_us_guide_q3.md":"e0d1552a","en_us_guide_q4.md":"935580a1","en_us_guide_q5.md":"6916b56e","en_us_guide_q6.md":"94c05cf7","en_us_guide_q7.md":"75c857c2","en_us_guide_servers.md":"f96f0a0e","en_us_guide_services.md":"c5de2f6c","en_us_guide_settings.md":"7e3ca56b","en_us_guide_tasks.md":"926aff97","en_us_index.md":"4c740f8b","guide_agent.md":"678c7d07","guide_agentq.md":"f457cf03","guide_api.md":"468772b9","guide_dashboard.md":"7e22b040","guide_dashboardq.md":"65bb3c89","guide_loginq.md":"1b0fcf93","guide_notifications.md":"abde0a78","guide_q1.md":"412e5eaf","guide_q2.md":"702e38ec","guide_q3.md":"3e19f217","guide_q4.md":"76788fc4","guide_q5.md":"24113023","guide_q6.md":"6cb72e9e","guide_q7.md":"478c2075","guide_servers.md":"bd64e498","guide_services.md":"3b743422","guide_settings.md":"5a73023e","guide_tasks.md":"939c3ef4","index.md":"3ef954bc"}
