{"en_us_guide_q3.md":"DcGYaHOG","en_us_guide_q2.md":"CpwqHh9D","developer_index.md":"CEC1ewQQ","en_us_case_case8.md":"D48Q8s_i","en_us_guide_q5.md":"CIVBnSaF","en_us_guide_ddns.md":"QUpCzrq2","en_us_guide_settings.md":"DZ12cquv","en_us_guide_services.md":"wX_zLY7H","en_us_guide_tasks.md":"H8x5Ze96","en_us_index.md":"CYBybmgK","guide_agent.md":"DMnm8J7a","en_us_case_case6.md":"CpODoyBF","en_us_case_case2.md":"PMCLDmJD","en_us_case_index.md":"wgLHh69c","en_us_developer_api.md":"cRo89E1R","case_case4.md":"Cqd4lcYe","en_us_case_case7.md":"CWWroIkF","case_case8.md":"Dj3ZUNQe","case_case6.md":"C1yQos86","developer_api.md":"C1iwMso0","case_case10.md":"CLZ04WW7","en_us_case_case9.md":"r1Aai7bw","guide_dashboard.md":"CVx32RFK","guide_nat.md":"B7LpsNg6","en_us_guide_group.md":"B8Ld_O1w","case_index.md":"LH7WLyrv","developer_i18n.md":"DJ4KKsIY","en_us_case_case3.md":"0hYqov5e","en_us_guide_q4.md":"DauKFJ50","en_us_case_case4.md":"Bb5pK15s","en_us_guide_q6.md":"BL3QCxre","en_us_developer_index.md":"C1jRFu21","en_us_guide_q7.md":"G0G1z3HQ","en_us_developer_i18n.md":"BKgfICGW","en_us_guide_q9.md":"CZIp5sZ0","en_us_guide_q8.md":"wNcJPsJz","en_us_guide_servers.md":"BzjZ8pID","en_us_guide_dashboardq.md":"3C2AYnkh","en_us_guide_notifications.md":"C_GZSMZl","en_us_guide_loginq.md":"D1XQzF1s","en_us_guide_dashboard.md":"C6JBx3Ix","case_case2.md":"BVa_CWhv","en_us_guide_agent.md":"DHGrWwOD","en_us_guide_q10.md":"B9ZcKvYc","en_us_guide_profile.md":"DaMPJ523","en_us_guide_user.md":"-IKItNaz","guide_agentq.md":"CrwNe_aH","en_us_guide_q11.md":"9HwdxIcA","case_case9.md":"BxI4CNDE","en_us_guide_q12.md":"CJ8p5Ju3","en_us_case_case5.md":"CxM-TBBz","en_us_guide_nat.md":"Dlwyv4Kp","en_us_case_case1.md":"BcZiAhpK","en_us_case_case10.md":"C28AdPg0","case_case5.md":"DDFfj5IM","case_case7.md":"BL3wTQgN","en_us_guide_q13.md":"Beni_ndc","case_case1.md":"INgUJ0PU","guide_q4.md":"DV-5NGQX","guide_ddns.md":"CV5_Z4CB","guide_user.md":"Ddvdej48","index.md":"C9oS2f4g","guide_group.md":"C4Zci2J9","guide_q5.md":"tKq3UzmY","guide_q6.md":"l06qancV","guide_q10.md":"cPrJmJvk","guide_profile.md":"BqgEasTo","guide_loginq.md":"D58Dvbfg","guide_tasks.md":"D2cWspA0","guide_settings.md":"D3jcsA4o","guide_api.md":"6u3ZBaAi","guide_q2.md":"ComuvTNp","guide_q7.md":"BsySWUTC","guide_services.md":"CPQlVRD1","guide_q8.md":"B0gsAsHG","en_us_guide_agentq.md":"DByRQmYm","guide_dashboardq.md":"D-Kuw1y2","case_case3.md":"DclEZYeE","guide_q13.md":"DrFk1_GH","en_us_guide_q14.md":"D40wd9ge","guide_q3.md":"ColuowDJ","guide_q12.md":"ayRWq--P","guide_q11.md":"CrJ7k0ix","en_us_guide_api.md":"ByY4lxaw","guide_q9.md":"6EXCX6Gl","guide_notifications.md":"DmmNvPEA","guide_q1.md":"C6bpmgge","guide_q14.md":"BNtT9RZJ","guide_servers.md":"Cfur2s34"}
